odoo9_addon_sale_stock_picking_return_invoicing-9.0.1.0.0-py2.7-nspkg.pth
odoo_addons/sale_stock_picking_return_invoicing/__openerp__.py
odoo_addons/sale_stock_picking_return_invoicing/__init__.py
odoo_addons/sale_stock_picking_return_invoicing/README.rst
odoo_addons/sale_stock_picking_return_invoicing/models/stock_move.py
odoo_addons/sale_stock_picking_return_invoicing/models/sale_order.py
odoo_addons/sale_stock_picking_return_invoicing/models/__init__.py
odoo_addons/sale_stock_picking_return_invoicing/i18n/es.po
odoo_addons/sale_stock_picking_return_invoicing/wizards/stock_return_picking.py
odoo_addons/sale_stock_picking_return_invoicing/wizards/__init__.py
odoo_addons/sale_stock_picking_return_invoicing/wizards/stock_return_picking_view.xml
odoo_addons/sale_stock_picking_return_invoicing/tests/test_refund.py
odoo_addons/sale_stock_picking_return_invoicing/tests/__init__.py
odoo_addons/sale_stock_picking_return_invoicing/static/description/icon.png
odoo9_addon_sale_stock_picking_return_invoicing-9.0.1.0.0.dist-info/top_level.txt
odoo9_addon_sale_stock_picking_return_invoicing-9.0.1.0.0.dist-info/WHEEL
odoo9_addon_sale_stock_picking_return_invoicing-9.0.1.0.0.dist-info/RECORD
odoo9_addon_sale_stock_picking_return_invoicing-9.0.1.0.0.dist-info/metadata.json
odoo9_addon_sale_stock_picking_return_invoicing-9.0.1.0.0.dist-info/DESCRIPTION.rst
odoo9_addon_sale_stock_picking_return_invoicing-9.0.1.0.0.dist-info/METADATA
odoo9_addon_sale_stock_picking_return_invoicing-9.0.1.0.0.dist-info/namespace_packages.txt
