Metadata-Version: 2.0
Name: odoo9-addon-sale-stock-picking-return-invoicing
Version: 9.0.1.0.0
Summary: Add an option to refund return pickings
Home-page: https://tecnativa.com/
Author: UNKNOWN
Author-email: UNKNOWN
License: AGPL-3
Platform: UNKNOWN
Requires-Dist: odoo (<9.1a,>=9.0a)
Classifier: Programming Language :: Python :: 2.7
Classifier: Framework :: Odoo
Classifier: License :: OSI Approved :: GNU Affero General Public License v3
